{            
    "name" : "FieldLocatorIntent",
    "entities" : [
        {
            "name" : "qustion_keyword",
            "contents": ["where", "what", "how"],
            "importance" : "require"
        },
        {
            "name" : "fielda_keyword",
            "contents": ["rig", "field", "well"],
            "importance" : "require"
        }, 
        {
            "name" : "distance_keyword",
            "contents" : ["nearest", "closest"],
            "importance" : "optionally"
        }
    ],

    "regex_entities" : [
        {
            "entity_name" : "field_distance_keywords",
            "regex_pattren": "[0-9]*",
            "apply_to" : ["in ", "around ", "within "],
            "importance" : "require"
        }
    ],

    "answers" : [
        "The closest {field_keyword} from {field_name} is {field_distance_keywords} {field_distance}"
    ] 

}
